braincube_connector/__init__.py
braincube_connector/bases/__init__.py
braincube_connector/bases/base.py
braincube_connector/bases/base_entity.py
braincube_connector/bases/resource_getter.py
braincube_connector/braincube.py
braincube_connector/client.py
braincube_connector/constants.py
braincube_connector/custom_types.py
braincube_connector/data/__init__.py
braincube_connector/data/conditions.py
braincube_connector/data/data.py
braincube_connector/instances.py
braincube_connector/memory_base/__init__.py
braincube_connector/memory_base/memory_base.py
braincube_connector/memory_base/nested_resources/__init__.py
braincube_connector/memory_base/nested_resources/condition_container.py
braincube_connector/memory_base/nested_resources/datagroup.py
braincube_connector/memory_base/nested_resources/event.py
braincube_connector/memory_base/nested_resources/job.py
braincube_connector/memory_base/nested_resources/mb_child.py
braincube_connector/memory_base/nested_resources/rule.py
braincube_connector/memory_base/nested_resources/variable.py
braincube_connector/parameters.py
braincube_connector/tools.py
braincube_connector-2.8.0.dist-info/METADATA
braincube_connector-2.8.0.dist-info/WHEEL
braincube_connector-2.8.0.dist-info/RECORD
