Metadata-Version: 2.3
Name: braincube-connector
Version: 2.8.0
Summary: python client to the braincube web services
License: MIT
Keywords: bc_connector,API,braincube
Author: Braincube
Author-email: io@braincube.com
Requires-Python: >=3.9,<4.0
Classifier: License :: OSI Approved :: MIT License
Classifier: Operating System :: OS Independent
Classifier: Programming Language :: Python :: 3
Classifier: Programming Language :: Python :: 3.9
Classifier: Programming Language :: Python :: 3.10
Classifier: Programming Language :: Python :: 3.11
Classifier: Programming Language :: Python :: 3.12
Classifier: Programming Language :: Python :: 3.13
Classifier: Programming Language :: Python :: 3.6
Classifier: Programming Language :: Python :: 3.7
Classifier: Programming Language :: Python :: 3.8
Requires-Dist: pandas (>=2.1.1,<3.0.0)
Requires-Dist: requests (>=2.23.0,<3.0.0)
Project-URL: Homepage, https://braincube-io.github.io/python-connector/
Project-URL: Repository, https://github.com/braincube-io/python-connector
